suffersync.py
suffersync-1.4.4.dist-info/LICENSE
suffersync-1.4.4.dist-info/METADATA
suffersync-1.4.4.dist-info/WHEEL
suffersync-1.4.4.dist-info/entry_points.txt
suffersync-1.4.4.dist-info/top_level.txt
suffersync-1.4.4.dist-info/RECORD
