Metadata-Version: 2.1
Name: suffersync
Version: 1.4.4
Summary: Syncs workouts from Wahoo SYSTM to intervals.icu
Home-page: https://github.com/bakermat/suffersync
Author: Bakermat
Author-email: 
License: MIT
License-File: LICENSE
Requires-Dist: requests >=2.26
